floatview/__init__.py
floatview/_version.py
floatview/dataexplorer.py
floatview/floatview.py
floatview/gluemanager.py
floatview/labextension/build_log.json
floatview/labextension/package.json
floatview/labextension/static/lib_index_js.5ceb5730f0715ce62ae9.js
floatview/labextension/static/lib_index_js.5ceb5730f0715ce62ae9.js.map
floatview/labextension/static/lib_plugin_js.2baac291f685581326ba.js
floatview/labextension/static/lib_plugin_js.2baac291f685581326ba.js.map
floatview/labextension/static/node_modules_css-loader_dist_runtime_api_js-node_modules_style-loader_dist_runtime_injectStyl-c3fd2f.7912c2c2238f92bc2c8e.js
floatview/labextension/static/node_modules_css-loader_dist_runtime_api_js-node_modules_style-loader_dist_runtime_injectStyl-c3fd2f.7912c2c2238f92bc2c8e.js.map
floatview/labextension/static/remoteEntry.d74df3979df5de1ae082.js
floatview/labextension/static/remoteEntry.d74df3979df5de1ae082.js.map
floatview/labextension/static/style.js
floatview/labextension/static/vendors-node_modules_jquery_dist_jquery_js.63b961f96d52ca4ac560.js
floatview/labextension/static/vendors-node_modules_jquery_dist_jquery_js.63b961f96d52ca4ac560.js.map
floatview/labextension/static/vendors-node_modules_jupyter-widgets_base_lib_index_js.c205a8d92877a6465479.js
floatview/labextension/static/vendors-node_modules_jupyter-widgets_base_lib_index_js.c205a8d92877a6465479.js.map
floatview/labextension/static/vendors-node_modules_jupyter-widgets_controls_lib_index_js.2e528eaefee600e2eab9.js
floatview/labextension/static/vendors-node_modules_jupyter-widgets_controls_lib_index_js.2e528eaefee600e2eab9.js.map
floatview/labextension/static/vendors-node_modules_jupyter-widgets_jupyterlab-manager_lib_index_js.b3b9e8a8cee9bc480933.js
floatview/labextension/static/vendors-node_modules_jupyter-widgets_jupyterlab-manager_lib_index_js.b3b9e8a8cee9bc480933.js.map
floatview/labextension/static/vendors-node_modules_underscore_modules_index-all_js.2e8b883707e15ebcee8a.js
floatview-0.4.1.dist-info/LICENSE.txt
floatview-0.4.1.dist-info/METADATA
floatview-0.4.1.dist-info/WHEEL
floatview-0.4.1.dist-info/top_level.txt
floatview-0.4.1.dist-info/RECORD
